moi/__init__.py
moi/client.py
moi/errors.py
moi/models.py
moi/options.py
moi/response.py
moi/sdk_client.py
moi/stream.py
moi_python_sdk-0.1.1.dev0.dist-info/licenses/LICENSE
moi_python_sdk-0.1.1.dev0.dist-info/METADATA
moi_python_sdk-0.1.1.dev0.dist-info/WHEEL
moi_python_sdk-0.1.1.dev0.dist-info/top_level.txt
moi_python_sdk-0.1.1.dev0.dist-info/RECORD
