Metadata-Version: 2.4
Name: moi-python-sdk
Version: 0.1.1.dev0
Summary: Python client SDK for the MatrixOrigin MOI Platform
Home-page: https://github.com/matrixorigin/moi-python-sdk
Author: MatrixOrigin
License: Apache-2.0
Project-URL: Homepage, https://github.com/matrixorigin/moi-python-sdk
Project-URL: Repository, https://github.com/matrixorigin/moi-python-sdk
Project-URL: Issues, https://github.com/matrixorigin/moi-python-sdk/issues
Classifier: Programming Language :: Python :: 3
Classifier: License :: OSI Approved :: Apache Software License
Classifier: Operating System :: OS Independent
Requires-Python: >=3.9
License-File: LICENSE
Requires-Dist: requests>=2.31.0
Dynamic: home-page
Dynamic: license-file
Dynamic: requires-python
